{
  "contract_version": "ao.atlas.workgraph.v0.1",
  "id": "ao-atlas-recommendation-wave-mission-710327df54728420",
  "target_instance": "ao-stack-p0b-contract-convergence-wave-v01",
  "nodes": [
    {
      "id": "mission-recommendation-p0b-contract-convergence-01",
      "status": "completed",
      "factory_task": {
        "contract_version": "ao.atlas.factory-task.v0.1",
        "id": "mission-recommendation-p0b-contract-convergence-01-task",
        "objective": "Bind Covenant event hashes to policy fields that affect ticket acceptance.",
        "target_factory_repo": "ao-atlas",
        "factory_folder": "factory/ao-atlas-recommendations/p0b-contract-convergence-01",
        "mutation_class": "low_risk_code",
        "acceptance_criteria": [
          "node gate, candidate record, rollback record, tests, verification, and readback evidence are recorded",
          "Atlas final response remains denied while ready work or exact next actions remain"
        ],
        "non_goals": [
          "do not execute Foundry work from Atlas",
          "do not widen AO authority or claim broad RSI"
        ],
        "write_scope": [
          "internal/atlas",
          "schemas",
          "examples",
          "docs/evidence"
        ],
        "required_gates": [
          "node_gate",
          "candidate_record",
          "rollback_record",
          "tests",
          "verification",
          "sentinel_public_safety",
          "promoter_no_promotion",
          "command_readback"
        ],
        "rollback_scope": [
          "revert node-specific Atlas changes and generated evidence"
        ],
        "verification_commands": [
          "go test ./... -count=1",
          "go vet ./...",
          "go build ./cmd/atlas",
          "scripts/production-readiness.sh",
          "scripts/atlas-foundry-roundtrip-smoke.sh"
        ],
        "required_evidence": [
          "source_digest:sha256:cf89a398e652f05a3c6bf713a973691e610a6c42b584fadaa75edad07c698d16",
          "source_recommendation:p0b-contract-convergence-01",
          "source_task_digest:sha256:f87cbea087ad742000a06da25d7ad4700ca082a6009ec5b81d8a96cb1a7ddbb8"
        ],
        "safety_limits": [
          "no provider calls",
          "no credential inspection",
          "no direct main mutation",
          "no release deploy publish upload tag",
          "no dependency updates without separate authorization",
          "no auth policy config widening",
          "no broad RSI claim"
        ],
        "authority_boundary": "atlas_recommendation_planning_only",
        "dependency_refs": null,
        "context_pack_refs": []
      },
      "dependencies": [],
      "blockers": [],
      "stitch_task": true
    },
    {
      "id": "mission-recommendation-p0b-contract-convergence-02",
      "status": "completed",
      "factory_task": {
        "contract_version": "ao.atlas.factory-task.v0.1",
        "id": "mission-recommendation-p0b-contract-convergence-02-task",
        "objective": "Add Covenant regression fixtures proving policy-field changes alter the event hash.",
        "target_factory_repo": "ao-atlas",
        "factory_folder": "factory/ao-atlas-recommendations/p0b-contract-convergence-02",
        "mutation_class": "low_risk_code",
        "acceptance_criteria": [
          "node gate, candidate record, rollback record, tests, verification, and readback evidence are recorded",
          "Atlas final response remains denied while ready work or exact next actions remain"
        ],
        "non_goals": [
          "do not execute Foundry work from Atlas",
          "do not widen AO authority or claim broad RSI"
        ],
        "write_scope": [
          "internal/atlas",
          "schemas",
          "examples",
          "docs/evidence"
        ],
        "required_gates": [
          "node_gate",
          "candidate_record",
          "rollback_record",
          "tests",
          "verification",
          "sentinel_public_safety",
          "promoter_no_promotion",
          "command_readback"
        ],
        "rollback_scope": [
          "revert node-specific Atlas changes and generated evidence"
        ],
        "verification_commands": [
          "go test ./... -count=1",
          "go vet ./...",
          "go build ./cmd/atlas",
          "scripts/production-readiness.sh",
          "scripts/atlas-foundry-roundtrip-smoke.sh"
        ],
        "required_evidence": [
          "source_digest:sha256:cf89a398e652f05a3c6bf713a973691e610a6c42b584fadaa75edad07c698d16",
          "source_recommendation:p0b-contract-convergence-02",
          "source_task_digest:sha256:cb16111e65c1a3edaeba235cb4c48b3715598580d6d7fcdae672ee479f9d3c65"
        ],
        "safety_limits": [
          "no provider calls",
          "no credential inspection",
          "no direct main mutation",
          "no release deploy publish upload tag",
          "no dependency updates without separate authorization",
          "no auth policy config widening",
          "no broad RSI claim"
        ],
        "authority_boundary": "atlas_recommendation_planning_only",
        "dependency_refs": [
          "mission-recommendation-p0b-contract-convergence-01"
        ],
        "context_pack_refs": []
      },
      "dependencies": [
        "mission-recommendation-p0b-contract-convergence-01"
      ],
      "blockers": [],
      "stitch_task": false
    },
    {
      "id": "mission-recommendation-p0b-contract-convergence-03",
      "status": "ready",
      "factory_task": {
        "contract_version": "ao.atlas.factory-task.v0.1",
        "id": "mission-recommendation-p0b-contract-convergence-03-task",
        "objective": "Add Command-to-Covenant accepted ticket fixture with canonical bytes and digest.",
        "target_factory_repo": "ao-atlas",
        "factory_folder": "factory/ao-atlas-recommendations/p0b-contract-convergence-03",
        "mutation_class": "low_risk_code",
        "acceptance_criteria": [
          "node gate, candidate record, rollback record, tests, verification, and readback evidence are recorded",
          "Atlas final response remains denied while ready work or exact next actions remain"
        ],
        "non_goals": [
          "do not execute Foundry work from Atlas",
          "do not widen AO authority or claim broad RSI"
        ],
        "write_scope": [
          "internal/atlas",
          "schemas",
          "examples",
          "docs/evidence"
        ],
        "required_gates": [
          "node_gate",
          "candidate_record",
          "rollback_record",
          "tests",
          "verification",
          "sentinel_public_safety",
          "promoter_no_promotion",
          "command_readback"
        ],
        "rollback_scope": [
          "revert node-specific Atlas changes and generated evidence"
        ],
        "verification_commands": [
          "go test ./... -count=1",
          "go vet ./...",
          "go build ./cmd/atlas",
          "scripts/production-readiness.sh",
          "scripts/atlas-foundry-roundtrip-smoke.sh"
        ],
        "required_evidence": [
          "source_digest:sha256:cf89a398e652f05a3c6bf713a973691e610a6c42b584fadaa75edad07c698d16",
          "source_recommendation:p0b-contract-convergence-03",
          "source_task_digest:sha256:58d1d00276050def5afe80c33808b00f491de9cf422775ff5882848935c92b2a"
        ],
        "safety_limits": [
          "no provider calls",
          "no credential inspection",
          "no direct main mutation",
          "no release deploy publish upload tag",
          "no dependency updates without separate authorization",
          "no auth policy config widening",
          "no broad RSI claim"
        ],
        "authority_boundary": "atlas_recommendation_planning_only",
        "dependency_refs": [
          "mission-recommendation-p0b-contract-convergence-02"
        ],
        "context_pack_refs": []
      },
      "dependencies": [
        "mission-recommendation-p0b-contract-convergence-02"
      ],
      "blockers": [],
      "stitch_task": false
    },
    {
      "id": "mission-recommendation-p0b-contract-convergence-04",
      "status": "ready",
      "factory_task": {
        "contract_version": "ao.atlas.factory-task.v0.1",
        "id": "mission-recommendation-p0b-contract-convergence-04-task",
        "objective": "Add Command-to-Covenant rejected ticket fixture preserving Covenant-native reason.",
        "target_factory_repo": "ao-atlas",
        "factory_folder": "factory/ao-atlas-recommendations/p0b-contract-convergence-04",
        "mutation_class": "low_risk_code",
        "acceptance_criteria": [
          "node gate, candidate record, rollback record, tests, verification, and readback evidence are recorded",
          "Atlas final response remains denied while ready work or exact next actions remain"
        ],
        "non_goals": [
          "do not execute Foundry work from Atlas",
          "do not widen AO authority or claim broad RSI"
        ],
        "write_scope": [
          "internal/atlas",
          "schemas",
          "examples",
          "docs/evidence"
        ],
        "required_gates": [
          "node_gate",
          "candidate_record",
          "rollback_record",
          "tests",
          "verification",
          "sentinel_public_safety",
          "promoter_no_promotion",
          "command_readback"
        ],
        "rollback_scope": [
          "revert node-specific Atlas changes and generated evidence"
        ],
        "verification_commands": [
          "go test ./... -count=1",
          "go vet ./...",
          "go build ./cmd/atlas",
          "scripts/production-readiness.sh",
          "scripts/atlas-foundry-roundtrip-smoke.sh"
        ],
        "required_evidence": [
          "source_digest:sha256:cf89a398e652f05a3c6bf713a973691e610a6c42b584fadaa75edad07c698d16",
          "source_recommendation:p0b-contract-convergence-04",
          "source_task_digest:sha256:a537908d2a87abcce22dea0c2df87b0d7bb44abced1a2d633379fc1b0186e5bd"
        ],
        "safety_limits": [
          "no provider calls",
          "no credential inspection",
          "no direct main mutation",
          "no release deploy publish upload tag",
          "no dependency updates without separate authorization",
          "no auth policy config widening",
          "no broad RSI claim"
        ],
        "authority_boundary": "atlas_recommendation_planning_only",
        "dependency_refs": [
          "mission-recommendation-p0b-contract-convergence-03"
        ],
        "context_pack_refs": []
      },
      "dependencies": [
        "mission-recommendation-p0b-contract-convergence-03"
      ],
      "blockers": [],
      "stitch_task": false
    },
    {
      "id": "mission-recommendation-p0b-contract-convergence-05",
      "status": "ready",
      "factory_task": {
        "contract_version": "ao.atlas.factory-task.v0.1",
        "id": "mission-recommendation-p0b-contract-convergence-05-task",
        "objective": "Quarantine Command validation paths that accept tickets Covenant rejects.",
        "target_factory_repo": "ao-atlas",
        "factory_folder": "factory/ao-atlas-recommendations/p0b-contract-convergence-05",
        "mutation_class": "low_risk_code",
        "acceptance_criteria": [
          "node gate, candidate record, rollback record, tests, verification, and readback evidence are recorded",
          "Atlas final response remains denied while ready work or exact next actions remain"
        ],
        "non_goals": [
          "do not execute Foundry work from Atlas",
          "do not widen AO authority or claim broad RSI"
        ],
        "write_scope": [
          "internal/atlas",
          "schemas",
          "examples",
          "docs/evidence"
        ],
        "required_gates": [
          "node_gate",
          "candidate_record",
          "rollback_record",
          "tests",
          "verification",
          "sentinel_public_safety",
          "promoter_no_promotion",
          "command_readback"
        ],
        "rollback_scope": [
          "revert node-specific Atlas changes and generated evidence"
        ],
        "verification_commands": [
          "go test ./... -count=1",
          "go vet ./...",
          "go build ./cmd/atlas",
          "scripts/production-readiness.sh",
          "scripts/atlas-foundry-roundtrip-smoke.sh"
        ],
        "required_evidence": [
          "source_digest:sha256:cf89a398e652f05a3c6bf713a973691e610a6c42b584fadaa75edad07c698d16",
          "source_recommendation:p0b-contract-convergence-05",
          "source_task_digest:sha256:e77bfef8dcd753a4dc9bfd8f437b66f9509c637fefbb4efbe216f2257871c8e6"
        ],
        "safety_limits": [
          "no provider calls",
          "no credential inspection",
          "no direct main mutation",
          "no release deploy publish upload tag",
          "no dependency updates without separate authorization",
          "no auth policy config widening",
          "no broad RSI claim"
        ],
        "authority_boundary": "atlas_recommendation_planning_only",
        "dependency_refs": [
          "mission-recommendation-p0b-contract-convergence-04"
        ],
        "context_pack_refs": []
      },
      "dependencies": [
        "mission-recommendation-p0b-contract-convergence-04"
      ],
      "blockers": [],
      "stitch_task": false
    },
    {
      "id": "mission-recommendation-p0b-contract-convergence-06",
      "status": "ready",
      "factory_task": {
        "contract_version": "ao.atlas.factory-task.v0.1",
        "id": "mission-recommendation-p0b-contract-convergence-06-task",
        "objective": "Add canonical ticket byte preservation across Command readback.",
        "target_factory_repo": "ao-atlas",
        "factory_folder": "factory/ao-atlas-recommendations/p0b-contract-convergence-06",
        "mutation_class": "low_risk_code",
        "acceptance_criteria": [
          "node gate, candidate record, rollback record, tests, verification, and readback evidence are recorded",
          "Atlas final response remains denied while ready work or exact next actions remain"
        ],
        "non_goals": [
          "do not execute Foundry work from Atlas",
          "do not widen AO authority or claim broad RSI"
        ],
        "write_scope": [
          "internal/atlas",
          "schemas",
          "examples",
          "docs/evidence"
        ],
        "required_gates": [
          "node_gate",
          "candidate_record",
          "rollback_record",
          "tests",
          "verification",
          "sentinel_public_safety",
          "promoter_no_promotion",
          "command_readback"
        ],
        "rollback_scope": [
          "revert node-specific Atlas changes and generated evidence"
        ],
        "verification_commands": [
          "go test ./... -count=1",
          "go vet ./...",
          "go build ./cmd/atlas",
          "scripts/production-readiness.sh",
          "scripts/atlas-foundry-roundtrip-smoke.sh"
        ],
        "required_evidence": [
          "source_digest:sha256:cf89a398e652f05a3c6bf713a973691e610a6c42b584fadaa75edad07c698d16",
          "source_recommendation:p0b-contract-convergence-06",
          "source_task_digest:sha256:12b48931c8b75255437a1b6fad2f9e4b0b07d93963f2cc3fbca8e45deef4bbc2"
        ],
        "safety_limits": [
          "no provider calls",
          "no credential inspection",
          "no direct main mutation",
          "no release deploy publish upload tag",
          "no dependency updates without separate authorization",
          "no auth policy config widening",
          "no broad RSI claim"
        ],
        "authority_boundary": "atlas_recommendation_planning_only",
        "dependency_refs": [
          "mission-recommendation-p0b-contract-convergence-05"
        ],
        "context_pack_refs": []
      },
      "dependencies": [
        "mission-recommendation-p0b-contract-convergence-05"
      ],
      "blockers": [],
      "stitch_task": true
    },
    {
      "id": "mission-recommendation-p0b-contract-convergence-07",
      "status": "ready",
      "factory_task": {
        "contract_version": "ao.atlas.factory-task.v0.1",
        "id": "mission-recommendation-p0b-contract-convergence-07-task",
        "objective": "Bind ticket digest into compact Command and Covenant evidence readbacks.",
        "target_factory_repo": "ao-atlas",
        "factory_folder": "factory/ao-atlas-recommendations/p0b-contract-convergence-07",
        "mutation_class": "low_risk_code",
        "acceptance_criteria": [
          "node gate, candidate record, rollback record, tests, verification, and readback evidence are recorded",
          "Atlas final response remains denied while ready work or exact next actions remain"
        ],
        "non_goals": [
          "do not execute Foundry work from Atlas",
          "do not widen AO authority or claim broad RSI"
        ],
        "write_scope": [
          "internal/atlas",
          "schemas",
          "examples",
          "docs/evidence"
        ],
        "required_gates": [
          "node_gate",
          "candidate_record",
          "rollback_record",
          "tests",
          "verification",
          "sentinel_public_safety",
          "promoter_no_promotion",
          "command_readback"
        ],
        "rollback_scope": [
          "revert node-specific Atlas changes and generated evidence"
        ],
        "verification_commands": [
          "go test ./... -count=1",
          "go vet ./...",
          "go build ./cmd/atlas",
          "scripts/production-readiness.sh",
          "scripts/atlas-foundry-roundtrip-smoke.sh"
        ],
        "required_evidence": [
          "source_digest:sha256:cf89a398e652f05a3c6bf713a973691e610a6c42b584fadaa75edad07c698d16",
          "source_recommendation:p0b-contract-convergence-07",
          "source_task_digest:sha256:eedb41d8d1be5cebbb92e539c4f56bf794e93e536b3d0b9fc49c270b7dfde812"
        ],
        "safety_limits": [
          "no provider calls",
          "no credential inspection",
          "no direct main mutation",
          "no release deploy publish upload tag",
          "no dependency updates without separate authorization",
          "no auth policy config widening",
          "no broad RSI claim"
        ],
        "authority_boundary": "atlas_recommendation_planning_only",
        "dependency_refs": [
          "mission-recommendation-p0b-contract-convergence-06"
        ],
        "context_pack_refs": []
      },
      "dependencies": [
        "mission-recommendation-p0b-contract-convergence-06"
      ],
      "blockers": [],
      "stitch_task": false
    },
    {
      "id": "mission-recommendation-p0b-contract-convergence-08",
      "status": "ready",
      "factory_task": {
        "contract_version": "ao.atlas.factory-task.v0.1",
        "id": "mission-recommendation-p0b-contract-convergence-08-task",
        "objective": "Add policy-hash mismatch rejection fixtures.",
        "target_factory_repo": "ao-atlas",
        "factory_folder": "factory/ao-atlas-recommendations/p0b-contract-convergence-08",
        "mutation_class": "low_risk_code",
        "acceptance_criteria": [
          "node gate, candidate record, rollback record, tests, verification, and readback evidence are recorded",
          "Atlas final response remains denied while ready work or exact next actions remain"
        ],
        "non_goals": [
          "do not execute Foundry work from Atlas",
          "do not widen AO authority or claim broad RSI"
        ],
        "write_scope": [
          "internal/atlas",
          "schemas",
          "examples",
          "docs/evidence"
        ],
        "required_gates": [
          "node_gate",
          "candidate_record",
          "rollback_record",
          "tests",
          "verification",
          "sentinel_public_safety",
          "promoter_no_promotion",
          "command_readback"
        ],
        "rollback_scope": [
          "revert node-specific Atlas changes and generated evidence"
        ],
        "verification_commands": [
          "go test ./... -count=1",
          "go vet ./...",
          "go build ./cmd/atlas",
          "scripts/production-readiness.sh",
          "scripts/atlas-foundry-roundtrip-smoke.sh"
        ],
        "required_evidence": [
          "source_digest:sha256:cf89a398e652f05a3c6bf713a973691e610a6c42b584fadaa75edad07c698d16",
          "source_recommendation:p0b-contract-convergence-08",
          "source_task_digest:sha256:c51f75d032e6fb34ab1a67040bdc448a7aef71348b5b0255728a53a313821a80"
        ],
        "safety_limits": [
          "no provider calls",
          "no credential inspection",
          "no direct main mutation",
          "no release deploy publish upload tag",
          "no dependency updates without separate authorization",
          "no auth policy config widening",
          "no broad RSI claim"
        ],
        "authority_boundary": "atlas_recommendation_planning_only",
        "dependency_refs": [
          "mission-recommendation-p0b-contract-convergence-07"
        ],
        "context_pack_refs": []
      },
      "dependencies": [
        "mission-recommendation-p0b-contract-convergence-07"
      ],
      "blockers": [],
      "stitch_task": false
    },
    {
      "id": "mission-recommendation-p0b-contract-convergence-09",
      "status": "ready",
      "factory_task": {
        "contract_version": "ao.atlas.factory-task.v0.1",
        "id": "mission-recommendation-p0b-contract-convergence-09-task",
        "objective": "Add stale ticket policy-version replay rejection fixtures.",
        "target_factory_repo": "ao-atlas",
        "factory_folder": "factory/ao-atlas-recommendations/p0b-contract-convergence-09",
        "mutation_class": "low_risk_code",
        "acceptance_criteria": [
          "node gate, candidate record, rollback record, tests, verification, and readback evidence are recorded",
          "Atlas final response remains denied while ready work or exact next actions remain"
        ],
        "non_goals": [
          "do not execute Foundry work from Atlas",
          "do not widen AO authority or claim broad RSI"
        ],
        "write_scope": [
          "internal/atlas",
          "schemas",
          "examples",
          "docs/evidence"
        ],
        "required_gates": [
          "node_gate",
          "candidate_record",
          "rollback_record",
          "tests",
          "verification",
          "sentinel_public_safety",
          "promoter_no_promotion",
          "command_readback"
        ],
        "rollback_scope": [
          "revert node-specific Atlas changes and generated evidence"
        ],
        "verification_commands": [
          "go test ./... -count=1",
          "go vet ./...",
          "go build ./cmd/atlas",
          "scripts/production-readiness.sh",
          "scripts/atlas-foundry-roundtrip-smoke.sh"
        ],
        "required_evidence": [
          "source_digest:sha256:cf89a398e652f05a3c6bf713a973691e610a6c42b584fadaa75edad07c698d16",
          "source_recommendation:p0b-contract-convergence-09",
          "source_task_digest:sha256:c68ad48d05dea40d3c4085e60031f59f49675357f0e3d5421f9840ac697903c6"
        ],
        "safety_limits": [
          "no provider calls",
          "no credential inspection",
          "no direct main mutation",
          "no release deploy publish upload tag",
          "no dependency updates without separate authorization",
          "no auth policy config widening",
          "no broad RSI claim"
        ],
        "authority_boundary": "atlas_recommendation_planning_only",
        "dependency_refs": [
          "mission-recommendation-p0b-contract-convergence-08"
        ],
        "context_pack_refs": []
      },
      "dependencies": [
        "mission-recommendation-p0b-contract-convergence-08"
      ],
      "blockers": [],
      "stitch_task": false
    },
    {
      "id": "mission-recommendation-p0b-contract-convergence-10",
      "status": "ready",
      "factory_task": {
        "contract_version": "ao.atlas.factory-task.v0.1",
        "id": "mission-recommendation-p0b-contract-convergence-10-task",
        "objective": "Add Covenant evidence readback with policy, ticket, and decision digests.",
        "target_factory_repo": "ao-atlas",
        "factory_folder": "factory/ao-atlas-recommendations/p0b-contract-convergence-10",
        "mutation_class": "low_risk_code",
        "acceptance_criteria": [
          "node gate, candidate record, rollback record, tests, verification, and readback evidence are recorded",
          "Atlas final response remains denied while ready work or exact next actions remain"
        ],
        "non_goals": [
          "do not execute Foundry work from Atlas",
          "do not widen AO authority or claim broad RSI"
        ],
        "write_scope": [
          "internal/atlas",
          "schemas",
          "examples",
          "docs/evidence"
        ],
        "required_gates": [
          "node_gate",
          "candidate_record",
          "rollback_record",
          "tests",
          "verification",
          "sentinel_public_safety",
          "promoter_no_promotion",
          "command_readback"
        ],
        "rollback_scope": [
          "revert node-specific Atlas changes and generated evidence"
        ],
        "verification_commands": [
          "go test ./... -count=1",
          "go vet ./...",
          "go build ./cmd/atlas",
          "scripts/production-readiness.sh",
          "scripts/atlas-foundry-roundtrip-smoke.sh"
        ],
        "required_evidence": [
          "source_digest:sha256:cf89a398e652f05a3c6bf713a973691e610a6c42b584fadaa75edad07c698d16",
          "source_recommendation:p0b-contract-convergence-10",
          "source_task_digest:sha256:2cd9e96114b7aca5d4ca5e065f0bd591c1afbef0d29873b8ab3e35833b2812cf"
        ],
        "safety_limits": [
          "no provider calls",
          "no credential inspection",
          "no direct main mutation",
          "no release deploy publish upload tag",
          "no dependency updates without separate authorization",
          "no auth policy config widening",
          "no broad RSI claim"
        ],
        "authority_boundary": "atlas_recommendation_planning_only",
        "dependency_refs": [
          "mission-recommendation-p0b-contract-convergence-09"
        ],
        "context_pack_refs": []
      },
      "dependencies": [
        "mission-recommendation-p0b-contract-convergence-09"
      ],
      "blockers": [],
      "stitch_task": false
    },
    {
      "id": "mission-recommendation-p0b-contract-convergence-11",
      "status": "ready",
      "factory_task": {
        "contract_version": "ao.atlas.factory-task.v0.1",
        "id": "mission-recommendation-p0b-contract-convergence-11-task",
        "objective": "Render Covenant-native rejection reasons in Command compact status.",
        "target_factory_repo": "ao-atlas",
        "factory_folder": "factory/ao-atlas-recommendations/p0b-contract-convergence-11",
        "mutation_class": "low_risk_code",
        "acceptance_criteria": [
          "node gate, candidate record, rollback record, tests, verification, and readback evidence are recorded",
          "Atlas final response remains denied while ready work or exact next actions remain"
        ],
        "non_goals": [
          "do not execute Foundry work from Atlas",
          "do not widen AO authority or claim broad RSI"
        ],
        "write_scope": [
          "internal/atlas",
          "schemas",
          "examples",
          "docs/evidence"
        ],
        "required_gates": [
          "node_gate",
          "candidate_record",
          "rollback_record",
          "tests",
          "verification",
          "sentinel_public_safety",
          "promoter_no_promotion",
          "command_readback"
        ],
        "rollback_scope": [
          "revert node-specific Atlas changes and generated evidence"
        ],
        "verification_commands": [
          "go test ./... -count=1",
          "go vet ./...",
          "go build ./cmd/atlas",
          "scripts/production-readiness.sh",
          "scripts/atlas-foundry-roundtrip-smoke.sh"
        ],
        "required_evidence": [
          "source_digest:sha256:cf89a398e652f05a3c6bf713a973691e610a6c42b584fadaa75edad07c698d16",
          "source_recommendation:p0b-contract-convergence-11",
          "source_task_digest:sha256:7d321d7b1393950c2527cbe4f75cf911b5620cc33a357908ea36b68e64ca1979"
        ],
        "safety_limits": [
          "no provider calls",
          "no credential inspection",
          "no direct main mutation",
          "no release deploy publish upload tag",
          "no dependency updates without separate authorization",
          "no auth policy config widening",
          "no broad RSI claim"
        ],
        "authority_boundary": "atlas_recommendation_planning_only",
        "dependency_refs": [
          "mission-recommendation-p0b-contract-convergence-10"
        ],
        "context_pack_refs": []
      },
      "dependencies": [
        "mission-recommendation-p0b-contract-convergence-10"
      ],
      "blockers": [],
      "stitch_task": true
    },
    {
      "id": "mission-recommendation-p0b-contract-convergence-12",
      "status": "ready",
      "factory_task": {
        "contract_version": "ao.atlas.factory-task.v0.1",
        "id": "mission-recommendation-p0b-contract-convergence-12-task",
        "objective": "Add Blueprint ticket-schema compatibility ledger entries.",
        "target_factory_repo": "ao-atlas",
        "factory_folder": "factory/ao-atlas-recommendations/p0b-contract-convergence-12",
        "mutation_class": "low_risk_code",
        "acceptance_criteria": [
          "node gate, candidate record, rollback record, tests, verification, and readback evidence are recorded",
          "Atlas final response remains denied while ready work or exact next actions remain"
        ],
        "non_goals": [
          "do not execute Foundry work from Atlas",
          "do not widen AO authority or claim broad RSI"
        ],
        "write_scope": [
          "internal/atlas",
          "schemas",
          "examples",
          "docs/evidence"
        ],
        "required_gates": [
          "node_gate",
          "candidate_record",
          "rollback_record",
          "tests",
          "verification",
          "sentinel_public_safety",
          "promoter_no_promotion",
          "command_readback"
        ],
        "rollback_scope": [
          "revert node-specific Atlas changes and generated evidence"
        ],
        "verification_commands": [
          "go test ./... -count=1",
          "go vet ./...",
          "go build ./cmd/atlas",
          "scripts/production-readiness.sh",
          "scripts/atlas-foundry-roundtrip-smoke.sh"
        ],
        "required_evidence": [
          "source_digest:sha256:cf89a398e652f05a3c6bf713a973691e610a6c42b584fadaa75edad07c698d16",
          "source_recommendation:p0b-contract-convergence-12",
          "source_task_digest:sha256:90ec5087969b268f4ae9a0e183133a6248add421dc163f890c9897dc0e6b347f"
        ],
        "safety_limits": [
          "no provider calls",
          "no credential inspection",
          "no direct main mutation",
          "no release deploy publish upload tag",
          "no dependency updates without separate authorization",
          "no auth policy config widening",
          "no broad RSI claim"
        ],
        "authority_boundary": "atlas_recommendation_planning_only",
        "dependency_refs": [
          "mission-recommendation-p0b-contract-convergence-11"
        ],
        "context_pack_refs": []
      },
      "dependencies": [
        "mission-recommendation-p0b-contract-convergence-11"
      ],
      "blockers": [],
      "stitch_task": false
    },
    {
      "id": "mission-recommendation-p0b-contract-convergence-13",
      "status": "ready",
      "factory_task": {
        "contract_version": "ao.atlas.factory-task.v0.1",
        "id": "mission-recommendation-p0b-contract-convergence-13-task",
        "objective": "Add Atlas ticket-schema compatibility ledger entries.",
        "target_factory_repo": "ao-atlas",
        "factory_folder": "factory/ao-atlas-recommendations/p0b-contract-convergence-13",
        "mutation_class": "low_risk_code",
        "acceptance_criteria": [
          "node gate, candidate record, rollback record, tests, verification, and readback evidence are recorded",
          "Atlas final response remains denied while ready work or exact next actions remain"
        ],
        "non_goals": [
          "do not execute Foundry work from Atlas",
          "do not widen AO authority or claim broad RSI"
        ],
        "write_scope": [
          "internal/atlas",
          "schemas",
          "examples",
          "docs/evidence"
        ],
        "required_gates": [
          "node_gate",
          "candidate_record",
          "rollback_record",
          "tests",
          "verification",
          "sentinel_public_safety",
          "promoter_no_promotion",
          "command_readback"
        ],
        "rollback_scope": [
          "revert node-specific Atlas changes and generated evidence"
        ],
        "verification_commands": [
          "go test ./... -count=1",
          "go vet ./...",
          "go build ./cmd/atlas",
          "scripts/production-readiness.sh",
          "scripts/atlas-foundry-roundtrip-smoke.sh"
        ],
        "required_evidence": [
          "source_digest:sha256:cf89a398e652f05a3c6bf713a973691e610a6c42b584fadaa75edad07c698d16",
          "source_recommendation:p0b-contract-convergence-13",
          "source_task_digest:sha256:f54749480044d3d717345967e185cb64ff69e213084ddaf2e57525dbfcf51c60"
        ],
        "safety_limits": [
          "no provider calls",
          "no credential inspection",
          "no direct main mutation",
          "no release deploy publish upload tag",
          "no dependency updates without separate authorization",
          "no auth policy config widening",
          "no broad RSI claim"
        ],
        "authority_boundary": "atlas_recommendation_planning_only",
        "dependency_refs": [
          "mission-recommendation-p0b-contract-convergence-12"
        ],
        "context_pack_refs": []
      },
      "dependencies": [
        "mission-recommendation-p0b-contract-convergence-12"
      ],
      "blockers": [],
      "stitch_task": false
    },
    {
      "id": "mission-recommendation-p0b-contract-convergence-14",
      "status": "ready",
      "factory_task": {
        "contract_version": "ao.atlas.factory-task.v0.1",
        "id": "mission-recommendation-p0b-contract-convergence-14-task",
        "objective": "Add Foundry ticket-schema compatibility ledger entries.",
        "target_factory_repo": "ao-atlas",
        "factory_folder": "factory/ao-atlas-recommendations/p0b-contract-convergence-14",
        "mutation_class": "low_risk_code",
        "acceptance_criteria": [
          "node gate, candidate record, rollback record, tests, verification, and readback evidence are recorded",
          "Atlas final response remains denied while ready work or exact next actions remain"
        ],
        "non_goals": [
          "do not execute Foundry work from Atlas",
          "do not widen AO authority or claim broad RSI"
        ],
        "write_scope": [
          "internal/atlas",
          "schemas",
          "examples",
          "docs/evidence"
        ],
        "required_gates": [
          "node_gate",
          "candidate_record",
          "rollback_record",
          "tests",
          "verification",
          "sentinel_public_safety",
          "promoter_no_promotion",
          "command_readback"
        ],
        "rollback_scope": [
          "revert node-specific Atlas changes and generated evidence"
        ],
        "verification_commands": [
          "go test ./... -count=1",
          "go vet ./...",
          "go build ./cmd/atlas",
          "scripts/production-readiness.sh",
          "scripts/atlas-foundry-roundtrip-smoke.sh"
        ],
        "required_evidence": [
          "source_digest:sha256:cf89a398e652f05a3c6bf713a973691e610a6c42b584fadaa75edad07c698d16",
          "source_recommendation:p0b-contract-convergence-14",
          "source_task_digest:sha256:b3d43b1108259c3cf42c15ba94cbfa9bdcb4576db5da885ea2bf14b2cd00b673"
        ],
        "safety_limits": [
          "no provider calls",
          "no credential inspection",
          "no direct main mutation",
          "no release deploy publish upload tag",
          "no dependency updates without separate authorization",
          "no auth policy config widening",
          "no broad RSI claim"
        ],
        "authority_boundary": "atlas_recommendation_planning_only",
        "dependency_refs": [
          "mission-recommendation-p0b-contract-convergence-13"
        ],
        "context_pack_refs": []
      },
      "dependencies": [
        "mission-recommendation-p0b-contract-convergence-13"
      ],
      "blockers": [],
      "stitch_task": false
    },
    {
      "id": "mission-recommendation-p0b-contract-convergence-15",
      "status": "ready",
      "factory_task": {
        "contract_version": "ao.atlas.factory-task.v0.1",
        "id": "mission-recommendation-p0b-contract-convergence-15-task",
        "objective": "Add Command ticket-schema producer/consumer compatibility entries.",
        "target_factory_repo": "ao-atlas",
        "factory_folder": "factory/ao-atlas-recommendations/p0b-contract-convergence-15",
        "mutation_class": "low_risk_code",
        "acceptance_criteria": [
          "node gate, candidate record, rollback record, tests, verification, and readback evidence are recorded",
          "Atlas final response remains denied while ready work or exact next actions remain"
        ],
        "non_goals": [
          "do not execute Foundry work from Atlas",
          "do not widen AO authority or claim broad RSI"
        ],
        "write_scope": [
          "internal/atlas",
          "schemas",
          "examples",
          "docs/evidence"
        ],
        "required_gates": [
          "node_gate",
          "candidate_record",
          "rollback_record",
          "tests",
          "verification",
          "sentinel_public_safety",
          "promoter_no_promotion",
          "command_readback"
        ],
        "rollback_scope": [
          "revert node-specific Atlas changes and generated evidence"
        ],
        "verification_commands": [
          "go test ./... -count=1",
          "go vet ./...",
          "go build ./cmd/atlas",
          "scripts/production-readiness.sh",
          "scripts/atlas-foundry-roundtrip-smoke.sh"
        ],
        "required_evidence": [
          "source_digest:sha256:cf89a398e652f05a3c6bf713a973691e610a6c42b584fadaa75edad07c698d16",
          "source_recommendation:p0b-contract-convergence-15",
          "source_task_digest:sha256:11cea08125ded62cb413961a2fc52c7fafa4df0b6380a9bcd5bdfacf0f57db71"
        ],
        "safety_limits": [
          "no provider calls",
          "no credential inspection",
          "no direct main mutation",
          "no release deploy publish upload tag",
          "no dependency updates without separate authorization",
          "no auth policy config widening",
          "no broad RSI claim"
        ],
        "authority_boundary": "atlas_recommendation_planning_only",
        "dependency_refs": [
          "mission-recommendation-p0b-contract-convergence-14"
        ],
        "context_pack_refs": []
      },
      "dependencies": [
        "mission-recommendation-p0b-contract-convergence-14"
      ],
      "blockers": [],
      "stitch_task": false
    },
    {
      "id": "mission-recommendation-p0b-contract-convergence-16",
      "status": "ready",
      "factory_task": {
        "contract_version": "ao.atlas.factory-task.v0.1",
        "id": "mission-recommendation-p0b-contract-convergence-16-task",
        "objective": "Add Covenant ticket-schema authority compatibility entries.",
        "target_factory_repo": "ao-atlas",
        "factory_folder": "factory/ao-atlas-recommendations/p0b-contract-convergence-16",
        "mutation_class": "low_risk_code",
        "acceptance_criteria": [
          "node gate, candidate record, rollback record, tests, verification, and readback evidence are recorded",
          "Atlas final response remains denied while ready work or exact next actions remain"
        ],
        "non_goals": [
          "do not execute Foundry work from Atlas",
          "do not widen AO authority or claim broad RSI"
        ],
        "write_scope": [
          "internal/atlas",
          "schemas",
          "examples",
          "docs/evidence"
        ],
        "required_gates": [
          "node_gate",
          "candidate_record",
          "rollback_record",
          "tests",
          "verification",
          "sentinel_public_safety",
          "promoter_no_promotion",
          "command_readback"
        ],
        "rollback_scope": [
          "revert node-specific Atlas changes and generated evidence"
        ],
        "verification_commands": [
          "go test ./... -count=1",
          "go vet ./...",
          "go build ./cmd/atlas",
          "scripts/production-readiness.sh",
          "scripts/atlas-foundry-roundtrip-smoke.sh"
        ],
        "required_evidence": [
          "source_digest:sha256:cf89a398e652f05a3c6bf713a973691e610a6c42b584fadaa75edad07c698d16",
          "source_recommendation:p0b-contract-convergence-16",
          "source_task_digest:sha256:fe3de3021d956c9478d326ba340c06a9f650ebf0c54816592787cb89e0a946d5"
        ],
        "safety_limits": [
          "no provider calls",
          "no credential inspection",
          "no direct main mutation",
          "no release deploy publish upload tag",
          "no dependency updates without separate authorization",
          "no auth policy config widening",
          "no broad RSI claim"
        ],
        "authority_boundary": "atlas_recommendation_planning_only",
        "dependency_refs": [
          "mission-recommendation-p0b-contract-convergence-15"
        ],
        "context_pack_refs": []
      },
      "dependencies": [
        "mission-recommendation-p0b-contract-convergence-15"
      ],
      "blockers": [],
      "stitch_task": true
    },
    {
      "id": "mission-recommendation-p0b-contract-convergence-17",
      "status": "ready",
      "factory_task": {
        "contract_version": "ao.atlas.factory-task.v0.1",
        "id": "mission-recommendation-p0b-contract-convergence-17-task",
        "objective": "Add public-safety wording scan for policy and ticket claims.",
        "target_factory_repo": "ao-atlas",
        "factory_folder": "factory/ao-atlas-recommendations/p0b-contract-convergence-17",
        "mutation_class": "low_risk_code",
        "acceptance_criteria": [
          "node gate, candidate record, rollback record, tests, verification, and readback evidence are recorded",
          "Atlas final response remains denied while ready work or exact next actions remain"
        ],
        "non_goals": [
          "do not execute Foundry work from Atlas",
          "do not widen AO authority or claim broad RSI"
        ],
        "write_scope": [
          "internal/atlas",
          "schemas",
          "examples",
          "docs/evidence"
        ],
        "required_gates": [
          "node_gate",
          "candidate_record",
          "rollback_record",
          "tests",
          "verification",
          "sentinel_public_safety",
          "promoter_no_promotion",
          "command_readback"
        ],
        "rollback_scope": [
          "revert node-specific Atlas changes and generated evidence"
        ],
        "verification_commands": [
          "go test ./... -count=1",
          "go vet ./...",
          "go build ./cmd/atlas",
          "scripts/production-readiness.sh",
          "scripts/atlas-foundry-roundtrip-smoke.sh"
        ],
        "required_evidence": [
          "source_digest:sha256:cf89a398e652f05a3c6bf713a973691e610a6c42b584fadaa75edad07c698d16",
          "source_recommendation:p0b-contract-convergence-17",
          "source_task_digest:sha256:53f8f705f992ae1215afa72fa2c967b04975d4a18447a9011ea5d34bca1105fa"
        ],
        "safety_limits": [
          "no provider calls",
          "no credential inspection",
          "no direct main mutation",
          "no release deploy publish upload tag",
          "no dependency updates without separate authorization",
          "no auth policy config widening",
          "no broad RSI claim"
        ],
        "authority_boundary": "atlas_recommendation_planning_only",
        "dependency_refs": [
          "mission-recommendation-p0b-contract-convergence-16"
        ],
        "context_pack_refs": []
      },
      "dependencies": [
        "mission-recommendation-p0b-contract-convergence-16"
      ],
      "blockers": [],
      "stitch_task": false
    },
    {
      "id": "mission-recommendation-p0b-contract-convergence-18",
      "status": "ready",
      "factory_task": {
        "contract_version": "ao.atlas.factory-task.v0.1",
        "id": "mission-recommendation-p0b-contract-convergence-18-task",
        "objective": "Add aggregate no-promotion/no-RSI rollup across P0-B nodes.",
        "target_factory_repo": "ao-atlas",
        "factory_folder": "factory/ao-atlas-recommendations/p0b-contract-convergence-18",
        "mutation_class": "low_risk_code",
        "acceptance_criteria": [
          "node gate, candidate record, rollback record, tests, verification, and readback evidence are recorded",
          "Atlas final response remains denied while ready work or exact next actions remain"
        ],
        "non_goals": [
          "do not execute Foundry work from Atlas",
          "do not widen AO authority or claim broad RSI"
        ],
        "write_scope": [
          "internal/atlas",
          "schemas",
          "examples",
          "docs/evidence"
        ],
        "required_gates": [
          "node_gate",
          "candidate_record",
          "rollback_record",
          "tests",
          "verification",
          "sentinel_public_safety",
          "promoter_no_promotion",
          "command_readback"
        ],
        "rollback_scope": [
          "revert node-specific Atlas changes and generated evidence"
        ],
        "verification_commands": [
          "go test ./... -count=1",
          "go vet ./...",
          "go build ./cmd/atlas",
          "scripts/production-readiness.sh",
          "scripts/atlas-foundry-roundtrip-smoke.sh"
        ],
        "required_evidence": [
          "source_digest:sha256:cf89a398e652f05a3c6bf713a973691e610a6c42b584fadaa75edad07c698d16",
          "source_recommendation:p0b-contract-convergence-18",
          "source_task_digest:sha256:6e37778e548e18cacf60dccd3d31801816f9b773649e997a9c0c853fb745098a"
        ],
        "safety_limits": [
          "no provider calls",
          "no credential inspection",
          "no direct main mutation",
          "no release deploy publish upload tag",
          "no dependency updates without separate authorization",
          "no auth policy config widening",
          "no broad RSI claim"
        ],
        "authority_boundary": "atlas_recommendation_planning_only",
        "dependency_refs": [
          "mission-recommendation-p0b-contract-convergence-17"
        ],
        "context_pack_refs": []
      },
      "dependencies": [
        "mission-recommendation-p0b-contract-convergence-17"
      ],
      "blockers": [],
      "stitch_task": false
    },
    {
      "id": "mission-recommendation-p0b-contract-convergence-19",
      "status": "ready",
      "factory_task": {
        "contract_version": "ao.atlas.factory-task.v0.1",
        "id": "mission-recommendation-p0b-contract-convergence-19-task",
        "objective": "Import P0-B Atlas recommendation readback into AO Mission without final response.",
        "target_factory_repo": "ao-atlas",
        "factory_folder": "factory/ao-atlas-recommendations/p0b-contract-convergence-19",
        "mutation_class": "low_risk_code",
        "acceptance_criteria": [
          "node gate, candidate record, rollback record, tests, verification, and readback evidence are recorded",
          "Atlas final response remains denied while ready work or exact next actions remain"
        ],
        "non_goals": [
          "do not execute Foundry work from Atlas",
          "do not widen AO authority or claim broad RSI"
        ],
        "write_scope": [
          "internal/atlas",
          "schemas",
          "examples",
          "docs/evidence"
        ],
        "required_gates": [
          "node_gate",
          "candidate_record",
          "rollback_record",
          "tests",
          "verification",
          "sentinel_public_safety",
          "promoter_no_promotion",
          "command_readback"
        ],
        "rollback_scope": [
          "revert node-specific Atlas changes and generated evidence"
        ],
        "verification_commands": [
          "go test ./... -count=1",
          "go vet ./...",
          "go build ./cmd/atlas",
          "scripts/production-readiness.sh",
          "scripts/atlas-foundry-roundtrip-smoke.sh"
        ],
        "required_evidence": [
          "source_digest:sha256:cf89a398e652f05a3c6bf713a973691e610a6c42b584fadaa75edad07c698d16",
          "source_recommendation:p0b-contract-convergence-19",
          "source_task_digest:sha256:281969d585cd49b87b00f66deb8095b9439fb9b39f9298d0ca0d462f23f0fa3b"
        ],
        "safety_limits": [
          "no provider calls",
          "no credential inspection",
          "no direct main mutation",
          "no release deploy publish upload tag",
          "no dependency updates without separate authorization",
          "no auth policy config widening",
          "no broad RSI claim"
        ],
        "authority_boundary": "atlas_recommendation_planning_only",
        "dependency_refs": [
          "mission-recommendation-p0b-contract-convergence-18"
        ],
        "context_pack_refs": []
      },
      "dependencies": [
        "mission-recommendation-p0b-contract-convergence-18"
      ],
      "blockers": [],
      "stitch_task": false
    },
    {
      "id": "mission-recommendation-p0b-contract-convergence-20",
      "status": "ready",
      "factory_task": {
        "contract_version": "ao.atlas.factory-task.v0.1",
        "id": "mission-recommendation-p0b-contract-convergence-20-task",
        "objective": "Emit Foundry import for exactly one ready P0-B implementation node.",
        "target_factory_repo": "ao-atlas",
        "factory_folder": "factory/ao-atlas-recommendations/p0b-contract-convergence-20",
        "mutation_class": "low_risk_code",
        "acceptance_criteria": [
          "node gate, candidate record, rollback record, tests, verification, and readback evidence are recorded",
          "Atlas final response remains denied while ready work or exact next actions remain"
        ],
        "non_goals": [
          "do not execute Foundry work from Atlas",
          "do not widen AO authority or claim broad RSI"
        ],
        "write_scope": [
          "internal/atlas",
          "schemas",
          "examples",
          "docs/evidence"
        ],
        "required_gates": [
          "node_gate",
          "candidate_record",
          "rollback_record",
          "tests",
          "verification",
          "sentinel_public_safety",
          "promoter_no_promotion",
          "command_readback"
        ],
        "rollback_scope": [
          "revert node-specific Atlas changes and generated evidence"
        ],
        "verification_commands": [
          "go test ./... -count=1",
          "go vet ./...",
          "go build ./cmd/atlas",
          "scripts/production-readiness.sh",
          "scripts/atlas-foundry-roundtrip-smoke.sh"
        ],
        "required_evidence": [
          "source_digest:sha256:cf89a398e652f05a3c6bf713a973691e610a6c42b584fadaa75edad07c698d16",
          "source_recommendation:p0b-contract-convergence-20",
          "source_task_digest:sha256:c54f33fcb32485270fefe497f2cb91ff2bdbcc4146daad313b4a3e0aa75c579b"
        ],
        "safety_limits": [
          "no provider calls",
          "no credential inspection",
          "no direct main mutation",
          "no release deploy publish upload tag",
          "no dependency updates without separate authorization",
          "no auth policy config widening",
          "no broad RSI claim"
        ],
        "authority_boundary": "atlas_recommendation_planning_only",
        "dependency_refs": [
          "mission-recommendation-p0b-contract-convergence-19"
        ],
        "context_pack_refs": []
      },
      "dependencies": [
        "mission-recommendation-p0b-contract-convergence-19"
      ],
      "blockers": [],
      "stitch_task": false
    },
    {
      "id": "mission-recommendation-p0b-contract-convergence-21",
      "status": "ready",
      "factory_task": {
        "contract_version": "ao.atlas.factory-task.v0.1",
        "id": "mission-recommendation-p0b-contract-convergence-21-task",
        "objective": "Add P0-B PR/CI ledger with merge-head and branch-cleanup fields.",
        "target_factory_repo": "ao-atlas",
        "factory_folder": "factory/ao-atlas-recommendations/p0b-contract-convergence-21",
        "mutation_class": "low_risk_code",
        "acceptance_criteria": [
          "node gate, candidate record, rollback record, tests, verification, and readback evidence are recorded",
          "Atlas final response remains denied while ready work or exact next actions remain"
        ],
        "non_goals": [
          "do not execute Foundry work from Atlas",
          "do not widen AO authority or claim broad RSI"
        ],
        "write_scope": [
          "internal/atlas",
          "schemas",
          "examples",
          "docs/evidence"
        ],
        "required_gates": [
          "node_gate",
          "candidate_record",
          "rollback_record",
          "tests",
          "verification",
          "sentinel_public_safety",
          "promoter_no_promotion",
          "command_readback"
        ],
        "rollback_scope": [
          "revert node-specific Atlas changes and generated evidence"
        ],
        "verification_commands": [
          "go test ./... -count=1",
          "go vet ./...",
          "go build ./cmd/atlas",
          "scripts/production-readiness.sh",
          "scripts/atlas-foundry-roundtrip-smoke.sh"
        ],
        "required_evidence": [
          "source_digest:sha256:cf89a398e652f05a3c6bf713a973691e610a6c42b584fadaa75edad07c698d16",
          "source_recommendation:p0b-contract-convergence-21",
          "source_task_digest:sha256:510ab6485bcf169d0a406fc75748fe6e06a9b6433e90f8924a631b95487da5b8"
        ],
        "safety_limits": [
          "no provider calls",
          "no credential inspection",
          "no direct main mutation",
          "no release deploy publish upload tag",
          "no dependency updates without separate authorization",
          "no auth policy config widening",
          "no broad RSI claim"
        ],
        "authority_boundary": "atlas_recommendation_planning_only",
        "dependency_refs": [
          "mission-recommendation-p0b-contract-convergence-20"
        ],
        "context_pack_refs": []
      },
      "dependencies": [
        "mission-recommendation-p0b-contract-convergence-20"
      ],
      "blockers": [],
      "stitch_task": true
    },
    {
      "id": "mission-recommendation-p0b-contract-convergence-22",
      "status": "ready",
      "factory_task": {
        "contract_version": "ao.atlas.factory-task.v0.1",
        "id": "mission-recommendation-p0b-contract-convergence-22-task",
        "objective": "Add long-running Windows CI wait-state telemetry for Covenant/Command shards.",
        "target_factory_repo": "ao-atlas",
        "factory_folder": "factory/ao-atlas-recommendations/p0b-contract-convergence-22",
        "mutation_class": "low_risk_code",
        "acceptance_criteria": [
          "node gate, candidate record, rollback record, tests, verification, and readback evidence are recorded",
          "Atlas final response remains denied while ready work or exact next actions remain"
        ],
        "non_goals": [
          "do not execute Foundry work from Atlas",
          "do not widen AO authority or claim broad RSI"
        ],
        "write_scope": [
          "internal/atlas",
          "schemas",
          "examples",
          "docs/evidence"
        ],
        "required_gates": [
          "node_gate",
          "candidate_record",
          "rollback_record",
          "tests",
          "verification",
          "sentinel_public_safety",
          "promoter_no_promotion",
          "command_readback"
        ],
        "rollback_scope": [
          "revert node-specific Atlas changes and generated evidence"
        ],
        "verification_commands": [
          "go test ./... -count=1",
          "go vet ./...",
          "go build ./cmd/atlas",
          "scripts/production-readiness.sh",
          "scripts/atlas-foundry-roundtrip-smoke.sh"
        ],
        "required_evidence": [
          "source_digest:sha256:cf89a398e652f05a3c6bf713a973691e610a6c42b584fadaa75edad07c698d16",
          "source_recommendation:p0b-contract-convergence-22",
          "source_task_digest:sha256:b1be5d0dea0cf0014f93717f960aef850e785279ae3c4f24a3af910fcf70f44d"
        ],
        "safety_limits": [
          "no provider calls",
          "no credential inspection",
          "no direct main mutation",
          "no release deploy publish upload tag",
          "no dependency updates without separate authorization",
          "no auth policy config widening",
          "no broad RSI claim"
        ],
        "authority_boundary": "atlas_recommendation_planning_only",
        "dependency_refs": [
          "mission-recommendation-p0b-contract-convergence-21"
        ],
        "context_pack_refs": []
      },
      "dependencies": [
        "mission-recommendation-p0b-contract-convergence-21"
      ],
      "blockers": [],
      "stitch_task": false
    },
    {
      "id": "mission-recommendation-p0b-contract-convergence-23",
      "status": "ready",
      "factory_task": {
        "contract_version": "ao.atlas.factory-task.v0.1",
        "id": "mission-recommendation-p0b-contract-convergence-23-task",
        "objective": "Audit rollback records for every P0-B node before closure.",
        "target_factory_repo": "ao-atlas",
        "factory_folder": "factory/ao-atlas-recommendations/p0b-contract-convergence-23",
        "mutation_class": "low_risk_code",
        "acceptance_criteria": [
          "node gate, candidate record, rollback record, tests, verification, and readback evidence are recorded",
          "Atlas final response remains denied while ready work or exact next actions remain"
        ],
        "non_goals": [
          "do not execute Foundry work from Atlas",
          "do not widen AO authority or claim broad RSI"
        ],
        "write_scope": [
          "internal/atlas",
          "schemas",
          "examples",
          "docs/evidence"
        ],
        "required_gates": [
          "node_gate",
          "candidate_record",
          "rollback_record",
          "tests",
          "verification",
          "sentinel_public_safety",
          "promoter_no_promotion",
          "command_readback"
        ],
        "rollback_scope": [
          "revert node-specific Atlas changes and generated evidence"
        ],
        "verification_commands": [
          "go test ./... -count=1",
          "go vet ./...",
          "go build ./cmd/atlas",
          "scripts/production-readiness.sh",
          "scripts/atlas-foundry-roundtrip-smoke.sh"
        ],
        "required_evidence": [
          "source_digest:sha256:cf89a398e652f05a3c6bf713a973691e610a6c42b584fadaa75edad07c698d16",
          "source_recommendation:p0b-contract-convergence-23",
          "source_task_digest:sha256:1bc9cfbe2730fdd16afc08ab28177916b5198637935d7316badafc205800adbf"
        ],
        "safety_limits": [
          "no provider calls",
          "no credential inspection",
          "no direct main mutation",
          "no release deploy publish upload tag",
          "no dependency updates without separate authorization",
          "no auth policy config widening",
          "no broad RSI claim"
        ],
        "authority_boundary": "atlas_recommendation_planning_only",
        "dependency_refs": [
          "mission-recommendation-p0b-contract-convergence-22"
        ],
        "context_pack_refs": []
      },
      "dependencies": [
        "mission-recommendation-p0b-contract-convergence-22"
      ],
      "blockers": [],
      "stitch_task": false
    },
    {
      "id": "mission-recommendation-p0b-contract-convergence-24",
      "status": "ready",
      "factory_task": {
        "contract_version": "ao.atlas.factory-task.v0.1",
        "id": "mission-recommendation-p0b-contract-convergence-24-task",
        "objective": "Bind Command and Promoter no-promotion agreement for P0-B.",
        "target_factory_repo": "ao-atlas",
        "factory_folder": "factory/ao-atlas-recommendations/p0b-contract-convergence-24",
        "mutation_class": "low_risk_code",
        "acceptance_criteria": [
          "node gate, candidate record, rollback record, tests, verification, and readback evidence are recorded",
          "Atlas final response remains denied while ready work or exact next actions remain"
        ],
        "non_goals": [
          "do not execute Foundry work from Atlas",
          "do not widen AO authority or claim broad RSI"
        ],
        "write_scope": [
          "internal/atlas",
          "schemas",
          "examples",
          "docs/evidence"
        ],
        "required_gates": [
          "node_gate",
          "candidate_record",
          "rollback_record",
          "tests",
          "verification",
          "sentinel_public_safety",
          "promoter_no_promotion",
          "command_readback"
        ],
        "rollback_scope": [
          "revert node-specific Atlas changes and generated evidence"
        ],
        "verification_commands": [
          "go test ./... -count=1",
          "go vet ./...",
          "go build ./cmd/atlas",
          "scripts/production-readiness.sh",
          "scripts/atlas-foundry-roundtrip-smoke.sh"
        ],
        "required_evidence": [
          "source_digest:sha256:cf89a398e652f05a3c6bf713a973691e610a6c42b584fadaa75edad07c698d16",
          "source_recommendation:p0b-contract-convergence-24",
          "source_task_digest:sha256:1b7360c0455e3f49860d2f77a77519e21ab534de34af1228495ba6e8053f2114"
        ],
        "safety_limits": [
          "no provider calls",
          "no credential inspection",
          "no direct main mutation",
          "no release deploy publish upload tag",
          "no dependency updates without separate authorization",
          "no auth policy config widening",
          "no broad RSI claim"
        ],
        "authority_boundary": "atlas_recommendation_planning_only",
        "dependency_refs": [
          "mission-recommendation-p0b-contract-convergence-23"
        ],
        "context_pack_refs": []
      },
      "dependencies": [
        "mission-recommendation-p0b-contract-convergence-23"
      ],
      "blockers": [],
      "stitch_task": false
    },
    {
      "id": "mission-recommendation-p0b-contract-convergence-25",
      "status": "ready",
      "factory_task": {
        "contract_version": "ao.atlas.factory-task.v0.1",
        "id": "mission-recommendation-p0b-contract-convergence-25-task",
        "objective": "Generate compaction-resume prompt from latest P0-B readback.",
        "target_factory_repo": "ao-atlas",
        "factory_folder": "factory/ao-atlas-recommendations/p0b-contract-convergence-25",
        "mutation_class": "low_risk_code",
        "acceptance_criteria": [
          "node gate, candidate record, rollback record, tests, verification, and readback evidence are recorded",
          "Atlas final response remains denied while ready work or exact next actions remain"
        ],
        "non_goals": [
          "do not execute Foundry work from Atlas",
          "do not widen AO authority or claim broad RSI"
        ],
        "write_scope": [
          "internal/atlas",
          "schemas",
          "examples",
          "docs/evidence"
        ],
        "required_gates": [
          "node_gate",
          "candidate_record",
          "rollback_record",
          "tests",
          "verification",
          "sentinel_public_safety",
          "promoter_no_promotion",
          "command_readback"
        ],
        "rollback_scope": [
          "revert node-specific Atlas changes and generated evidence"
        ],
        "verification_commands": [
          "go test ./... -count=1",
          "go vet ./...",
          "go build ./cmd/atlas",
          "scripts/production-readiness.sh",
          "scripts/atlas-foundry-roundtrip-smoke.sh"
        ],
        "required_evidence": [
          "source_digest:sha256:cf89a398e652f05a3c6bf713a973691e610a6c42b584fadaa75edad07c698d16",
          "source_recommendation:p0b-contract-convergence-25",
          "source_task_digest:sha256:f7e2ff147601d943887803abea619b10b4755820166fd176d986256c61013391"
        ],
        "safety_limits": [
          "no provider calls",
          "no credential inspection",
          "no direct main mutation",
          "no release deploy publish upload tag",
          "no dependency updates without separate authorization",
          "no auth policy config widening",
          "no broad RSI claim"
        ],
        "authority_boundary": "atlas_recommendation_planning_only",
        "dependency_refs": [
          "mission-recommendation-p0b-contract-convergence-24"
        ],
        "context_pack_refs": []
      },
      "dependencies": [
        "mission-recommendation-p0b-contract-convergence-24"
      ],
      "blockers": [],
      "stitch_task": false
    },
    {
      "id": "mission-recommendation-p0b-contract-convergence-26",
      "status": "ready",
      "factory_task": {
        "contract_version": "ao.atlas.factory-task.v0.1",
        "id": "mission-recommendation-p0b-contract-convergence-26-task",
        "objective": "Validate every P0-B evidence JSON file in one command.",
        "target_factory_repo": "ao-atlas",
        "factory_folder": "factory/ao-atlas-recommendations/p0b-contract-convergence-26",
        "mutation_class": "low_risk_code",
        "acceptance_criteria": [
          "node gate, candidate record, rollback record, tests, verification, and readback evidence are recorded",
          "Atlas final response remains denied while ready work or exact next actions remain"
        ],
        "non_goals": [
          "do not execute Foundry work from Atlas",
          "do not widen AO authority or claim broad RSI"
        ],
        "write_scope": [
          "internal/atlas",
          "schemas",
          "examples",
          "docs/evidence"
        ],
        "required_gates": [
          "node_gate",
          "candidate_record",
          "rollback_record",
          "tests",
          "verification",
          "sentinel_public_safety",
          "promoter_no_promotion",
          "command_readback"
        ],
        "rollback_scope": [
          "revert node-specific Atlas changes and generated evidence"
        ],
        "verification_commands": [
          "go test ./... -count=1",
          "go vet ./...",
          "go build ./cmd/atlas",
          "scripts/production-readiness.sh",
          "scripts/atlas-foundry-roundtrip-smoke.sh"
        ],
        "required_evidence": [
          "source_digest:sha256:cf89a398e652f05a3c6bf713a973691e610a6c42b584fadaa75edad07c698d16",
          "source_recommendation:p0b-contract-convergence-26",
          "source_task_digest:sha256:0572b829f993461f31b82f9715a83baf9b1016219ea5ac0859c329be524335f9"
        ],
        "safety_limits": [
          "no provider calls",
          "no credential inspection",
          "no direct main mutation",
          "no release deploy publish upload tag",
          "no dependency updates without separate authorization",
          "no auth policy config widening",
          "no broad RSI claim"
        ],
        "authority_boundary": "atlas_recommendation_planning_only",
        "dependency_refs": [
          "mission-recommendation-p0b-contract-convergence-25"
        ],
        "context_pack_refs": []
      },
      "dependencies": [
        "mission-recommendation-p0b-contract-convergence-25"
      ],
      "blockers": [],
      "stitch_task": true
    },
    {
      "id": "mission-recommendation-p0b-contract-convergence-27",
      "status": "ready",
      "factory_task": {
        "contract_version": "ao.atlas.factory-task.v0.1",
        "id": "mission-recommendation-p0b-contract-convergence-27-task",
        "objective": "Record post-merge cleanup evidence after branch deletion.",
        "target_factory_repo": "ao-atlas",
        "factory_folder": "factory/ao-atlas-recommendations/p0b-contract-convergence-27",
        "mutation_class": "low_risk_code",
        "acceptance_criteria": [
          "node gate, candidate record, rollback record, tests, verification, and readback evidence are recorded",
          "Atlas final response remains denied while ready work or exact next actions remain"
        ],
        "non_goals": [
          "do not execute Foundry work from Atlas",
          "do not widen AO authority or claim broad RSI"
        ],
        "write_scope": [
          "internal/atlas",
          "schemas",
          "examples",
          "docs/evidence"
        ],
        "required_gates": [
          "node_gate",
          "candidate_record",
          "rollback_record",
          "tests",
          "verification",
          "sentinel_public_safety",
          "promoter_no_promotion",
          "command_readback"
        ],
        "rollback_scope": [
          "revert node-specific Atlas changes and generated evidence"
        ],
        "verification_commands": [
          "go test ./... -count=1",
          "go vet ./...",
          "go build ./cmd/atlas",
          "scripts/production-readiness.sh",
          "scripts/atlas-foundry-roundtrip-smoke.sh"
        ],
        "required_evidence": [
          "source_digest:sha256:cf89a398e652f05a3c6bf713a973691e610a6c42b584fadaa75edad07c698d16",
          "source_recommendation:p0b-contract-convergence-27",
          "source_task_digest:sha256:670d8e325e33b3c3b11e847a48e5235769cd4ca42b261b4ec2c363c5524db37c"
        ],
        "safety_limits": [
          "no provider calls",
          "no credential inspection",
          "no direct main mutation",
          "no release deploy publish upload tag",
          "no dependency updates without separate authorization",
          "no auth policy config widening",
          "no broad RSI claim"
        ],
        "authority_boundary": "atlas_recommendation_planning_only",
        "dependency_refs": [
          "mission-recommendation-p0b-contract-convergence-26"
        ],
        "context_pack_refs": []
      },
      "dependencies": [
        "mission-recommendation-p0b-contract-convergence-26"
      ],
      "blockers": [],
      "stitch_task": false
    },
    {
      "id": "mission-recommendation-p0b-contract-convergence-28",
      "status": "ready",
      "factory_task": {
        "contract_version": "ao.atlas.factory-task.v0.1",
        "id": "mission-recommendation-p0b-contract-convergence-28-task",
        "objective": "Generate final operator summary from the P0-B terminal readback.",
        "target_factory_repo": "ao-atlas",
        "factory_folder": "factory/ao-atlas-recommendations/p0b-contract-convergence-28",
        "mutation_class": "low_risk_code",
        "acceptance_criteria": [
          "node gate, candidate record, rollback record, tests, verification, and readback evidence are recorded",
          "Atlas final response remains denied while ready work or exact next actions remain"
        ],
        "non_goals": [
          "do not execute Foundry work from Atlas",
          "do not widen AO authority or claim broad RSI"
        ],
        "write_scope": [
          "internal/atlas",
          "schemas",
          "examples",
          "docs/evidence"
        ],
        "required_gates": [
          "node_gate",
          "candidate_record",
          "rollback_record",
          "tests",
          "verification",
          "sentinel_public_safety",
          "promoter_no_promotion",
          "command_readback"
        ],
        "rollback_scope": [
          "revert node-specific Atlas changes and generated evidence"
        ],
        "verification_commands": [
          "go test ./... -count=1",
          "go vet ./...",
          "go build ./cmd/atlas",
          "scripts/production-readiness.sh",
          "scripts/atlas-foundry-roundtrip-smoke.sh"
        ],
        "required_evidence": [
          "source_digest:sha256:cf89a398e652f05a3c6bf713a973691e610a6c42b584fadaa75edad07c698d16",
          "source_recommendation:p0b-contract-convergence-28",
          "source_task_digest:sha256:daa053517f0f48b9add5946fb3b573c3b439403a4670f0ab5f00743d8f256eda"
        ],
        "safety_limits": [
          "no provider calls",
          "no credential inspection",
          "no direct main mutation",
          "no release deploy publish upload tag",
          "no dependency updates without separate authorization",
          "no auth policy config widening",
          "no broad RSI claim"
        ],
        "authority_boundary": "atlas_recommendation_planning_only",
        "dependency_refs": [
          "mission-recommendation-p0b-contract-convergence-27"
        ],
        "context_pack_refs": []
      },
      "dependencies": [
        "mission-recommendation-p0b-contract-convergence-27"
      ],
      "blockers": [],
      "stitch_task": false
    },
    {
      "id": "mission-recommendation-p0b-contract-convergence-29",
      "status": "ready",
      "factory_task": {
        "contract_version": "ao.atlas.factory-task.v0.1",
        "id": "mission-recommendation-p0b-contract-convergence-29-task",
        "objective": "Bridge P0-B closure into P0-C Mission-to-Foundry readiness criteria.",
        "target_factory_repo": "ao-atlas",
        "factory_folder": "factory/ao-atlas-recommendations/p0b-contract-convergence-29",
        "mutation_class": "low_risk_code",
        "acceptance_criteria": [
          "node gate, candidate record, rollback record, tests, verification, and readback evidence are recorded",
          "Atlas final response remains denied while ready work or exact next actions remain"
        ],
        "non_goals": [
          "do not execute Foundry work from Atlas",
          "do not widen AO authority or claim broad RSI"
        ],
        "write_scope": [
          "internal/atlas",
          "schemas",
          "examples",
          "docs/evidence"
        ],
        "required_gates": [
          "node_gate",
          "candidate_record",
          "rollback_record",
          "tests",
          "verification",
          "sentinel_public_safety",
          "promoter_no_promotion",
          "command_readback"
        ],
        "rollback_scope": [
          "revert node-specific Atlas changes and generated evidence"
        ],
        "verification_commands": [
          "go test ./... -count=1",
          "go vet ./...",
          "go build ./cmd/atlas",
          "scripts/production-readiness.sh",
          "scripts/atlas-foundry-roundtrip-smoke.sh"
        ],
        "required_evidence": [
          "source_digest:sha256:cf89a398e652f05a3c6bf713a973691e610a6c42b584fadaa75edad07c698d16",
          "source_recommendation:p0b-contract-convergence-29",
          "source_task_digest:sha256:9553bc2f58e1f1c192a7cc17549236c3fd4585f1f9ff5bf9dc0a129f39c9377a"
        ],
        "safety_limits": [
          "no provider calls",
          "no credential inspection",
          "no direct main mutation",
          "no release deploy publish upload tag",
          "no dependency updates without separate authorization",
          "no auth policy config widening",
          "no broad RSI claim"
        ],
        "authority_boundary": "atlas_recommendation_planning_only",
        "dependency_refs": [
          "mission-recommendation-p0b-contract-convergence-28"
        ],
        "context_pack_refs": []
      },
      "dependencies": [
        "mission-recommendation-p0b-contract-convergence-28"
      ],
      "blockers": [],
      "stitch_task": false
    },
    {
      "id": "mission-recommendation-p0b-contract-convergence-30",
      "status": "ready",
      "factory_task": {
        "contract_version": "ao.atlas.factory-task.v0.1",
        "id": "mission-recommendation-p0b-contract-convergence-30-task",
        "objective": "Generate P0-C Mission to Foundry real complete-path handoff.",
        "target_factory_repo": "ao-atlas",
        "factory_folder": "factory/ao-atlas-recommendations/p0b-contract-convergence-30",
        "mutation_class": "low_risk_code",
        "acceptance_criteria": [
          "node gate, candidate record, rollback record, tests, verification, and readback evidence are recorded",
          "Atlas final response remains denied while ready work or exact next actions remain"
        ],
        "non_goals": [
          "do not execute Foundry work from Atlas",
          "do not widen AO authority or claim broad RSI"
        ],
        "write_scope": [
          "internal/atlas",
          "schemas",
          "examples",
          "docs/evidence"
        ],
        "required_gates": [
          "node_gate",
          "candidate_record",
          "rollback_record",
          "tests",
          "verification",
          "sentinel_public_safety",
          "promoter_no_promotion",
          "command_readback"
        ],
        "rollback_scope": [
          "revert node-specific Atlas changes and generated evidence"
        ],
        "verification_commands": [
          "go test ./... -count=1",
          "go vet ./...",
          "go build ./cmd/atlas",
          "scripts/production-readiness.sh",
          "scripts/atlas-foundry-roundtrip-smoke.sh"
        ],
        "required_evidence": [
          "source_digest:sha256:cf89a398e652f05a3c6bf713a973691e610a6c42b584fadaa75edad07c698d16",
          "source_recommendation:p0b-contract-convergence-30",
          "source_task_digest:sha256:8baf6b0bcc1908ae8c256cabaf9325f7224dbd8393d6a07687fa8959095e5890"
        ],
        "safety_limits": [
          "no provider calls",
          "no credential inspection",
          "no direct main mutation",
          "no release deploy publish upload tag",
          "no dependency updates without separate authorization",
          "no auth policy config widening",
          "no broad RSI claim"
        ],
        "authority_boundary": "atlas_recommendation_planning_only",
        "dependency_refs": [
          "mission-recommendation-p0b-contract-convergence-29"
        ],
        "context_pack_refs": []
      },
      "dependencies": [
        "mission-recommendation-p0b-contract-convergence-29"
      ],
      "blockers": [],
      "stitch_task": false
    }
  ]
}
