{
  "schema": "ao.atlas.consolidation-implementation-evidence.v0.1",
  "kind": "covenant_generated_go_type_compatibility",
  "node_id": "mission-recommendation-month2-contract-convergence-22",
  "task_id": "mission-recommendation-month2-contract-convergence-22-task",
  "source_owner": "ao-covenant",
  "source_digest": "sha256:6b1b908b7d4dd9150513faa30b69f4d90692c9f03f3992e8eab46bbb38ca1857",
  "evidence_class": "compatibility_audit",
  "status": "blocked_missing_generated_type_contract",
  "producer": "ao-covenant",
  "consumer": "ao-control",
  "compatibility_status": "planning_only",
  "required_gates": [
    "generator ownership",
    "regeneration command",
    "canonical JSON vectors",
    "round-trip smoke",
    "unknown field policy",
    "cross-consumer schema version gate"
  ],
  "current_gap": "Covenant currently validates schemas and uses handwritten Go types; no generated type artifact or generator contract was found in the inspected source",
  "compatibility_gate": "blocked_until_generated_type_strategy_and_consumer_vectors_exist",
  "safe_to_execute": false,
  "planning_only": true,
  "no_promotion_requested": true,
  "promotion_granted": false,
  "claims_authority_advance": false,
  "rsi_remains_denied": true,
  "schedules_work": false,
  "executes_work": false,
  "approves_work": false,
  "mutates_repositories": false
}
